benchmarks/__init__.py
benchmarks/benchmarks.py
pymongoarrow/__init__.py
pymongoarrow/api.py
pymongoarrow/bson-1.0.dll
pymongoarrow/context.py
pymongoarrow/errors.py
pymongoarrow/lib.cp310-win_amd64.pyd
pymongoarrow/lib.pyx
pymongoarrow/libarrow.pxd
pymongoarrow/libbson.pxd
pymongoarrow/monkey.py
pymongoarrow/pandas_types.py
pymongoarrow/result.py
pymongoarrow/schema.py
pymongoarrow/types.py
pymongoarrow/version.py
test/pandas_types/__init__.py
test/pandas_types/test_binary.py
test/pandas_types/test_code.py
test/pandas_types/test_decimal128.py
test/pandas_types/test_objectid.py
test/pandas_types/util.py
pymongoarrow-1.12.0.dist-info/LICENSE
pymongoarrow-1.12.0.dist-info/METADATA
pymongoarrow-1.12.0.dist-info/WHEEL
pymongoarrow-1.12.0.dist-info/top_level.txt
pymongoarrow-1.12.0.dist-info/RECORD
