Metadata-Version: 2.1
Name: pymongoarrow
Version: 1.12.0
Summary: Tools for using NumPy, Pandas, Polars, and PyArrow with MongoDB
Author: Prashant Mital
Maintainer: MongoDB, Inc.
License: Apache License, Version 2.0
Project-URL: Homepage, https://www.mongodb.org
Project-URL: Documentation, https://mongo-arrow.readthedocs.io
Project-URL: Source, https://github.com/mongodb-labs/mongo-arrow/tree/main/bindings/python
Project-URL: Tracker, https://jira.mongodb.org/projects/INTPYTHON/issues
Keywords: mongo,mongodb,pymongo,arrow,bson,numpy,pandas,polars
Platform: Linux
Platform: Mac OS X
Classifier: Development Status :: 3 - Alpha
Classifier: Intended Audience :: Developers
Classifier: Intended Audience :: Science/Research
Classifier: License :: OSI Approved :: Apache Software License
Classifier: Operating System :: MacOS :: MacOS X
Classifier: Operating System :: POSIX
Classifier: Programming Language :: Python :: 3
Classifier: Programming Language :: Python :: 3 :: Only
Classifier: Programming Language :: Python :: 3.10
Classifier: Programming Language :: Python :: 3.11
Classifier: Programming Language :: Python :: 3.12
Classifier: Programming Language :: Python :: 3.13
Classifier: Programming Language :: Python :: 3.14
Classifier: Programming Language :: Python :: Implementation :: CPython
Classifier: Topic :: Database
Requires-Python: >=3.10
License-File: LICENSE
Requires-Dist: pyarrow <23.1,>=23.0
Requires-Dist: pymongo <5,>=4.4
Requires-Dist: packaging >=23.2
Requires-Dist: numpy >=1.26 ; python_version < "3.11"
Requires-Dist: numpy >=2.1.0 ; python_version >= "3.11"
Provides-Extra: test
Requires-Dist: pytz >=2025.2 ; extra == 'test'
Requires-Dist: pytest >=8.0 ; extra == 'test'
Provides-Extra: test-pandas
Requires-Dist: pandas >=2.0.3 ; (python_version < "3.11") and extra == 'test-pandas'
Requires-Dist: numpy <2 ; (python_version < "3.11") and extra == 'test-pandas'
Requires-Dist: pandas >=3.0 ; (python_version >= "3.11") and extra == 'test-pandas'
Provides-Extra: test-polars
Requires-Dist: polars >=1.10 ; extra == 'test-polars'
